setup.py
NgaCodeConverter/__init__.py
NgaCodeConverter/converter.py
NgaCodeConverter/parser.py
NgaCodeConverter.egg-info/PKG-INFO
NgaCodeConverter.egg-info/SOURCES.txt
NgaCodeConverter.egg-info/dependency_links.txt
NgaCodeConverter.egg-info/requires.txt
NgaCodeConverter.egg-info/top_level.txt
NgaCodeConverter/data/myconf.conf