Metadata-Version: 1.0
Name: NgaCodeConverter
Version: 0.2.1
Summary: A tool to convert HTML/Markdown code into NGA code format.
Home-page: https://github.com/sjn4048/NgaCodeConverter
Author: Jianing Shi
Author-email: sjn4048@gmail.com
License: Apache 2.0
Platform: all
